librt/__init__.pyi
librt/base64.cpython-310-i386-linux-gnu.so
librt/base64.pyi
librt/internal.cpython-310-i386-linux-gnu.so
librt/internal.pyi
librt/py.typed
librt/strings.cpython-310-i386-linux-gnu.so
librt/strings.pyi
librt-0.7.5.dist-info/METADATA
librt-0.7.5.dist-info/WHEEL
librt-0.7.5.dist-info/top_level.txt
librt-0.7.5.dist-info/RECORD
librt-0.7.5.dist-info/licenses/LICENSE
